pmxbot/__init__.py
pmxbot/__main__.py
pmxbot/asciilogo.txt
pmxbot/commands.py
pmxbot/config_.py
pmxbot/core.py
pmxbot/dictlib.py
pmxbot/example usage.txt
pmxbot/http.py
pmxbot/irc.py
pmxbot/itertools.py
pmxbot/karma.py
pmxbot/klingonisms.txt
pmxbot/logging.py
pmxbot/murphy's laws.txt
pmxbot/notify.py
pmxbot/phrases.py
pmxbot/quotes.py
pmxbot/rolls.py
pmxbot/slack.py
pmxbot/social strategies.txt
pmxbot/stack.py
pmxbot/storage.py
pmxbot/system.py
pmxbot/util.py
pmxbot/routines/dedup-karma.py
pmxbot/routines/migrate-all.py
pmxbot/routines/rebuild-recent.py
pmxbot/testing/__init__.py
pmxbot/testing/fixtures.py
pmxbot/web/__init__.py
pmxbot/web/__main__.py
pmxbot/web/viewer.py
pmxbot/web/templates/Autolinker.js
pmxbot/web/templates/__init__.py
pmxbot/web/templates/base.html
pmxbot/web/templates/channel.html
pmxbot/web/templates/day.html
pmxbot/web/templates/help.html
pmxbot/web/templates/index.html
pmxbot/web/templates/karma.html
pmxbot/web/templates/pmxbot.png
pmxbot/web/templates/search.html
pmxbot-1122.17.0.dist-info/LICENSE
pmxbot-1122.17.0.dist-info/METADATA
pmxbot-1122.17.0.dist-info/WHEEL
pmxbot-1122.17.0.dist-info/entry_points.txt
pmxbot-1122.17.0.dist-info/top_level.txt
pmxbot-1122.17.0.dist-info/RECORD
