Metadata-Version: 2.1
Name: pmxbot
Version: 1122.17.0
Summary: IRC bot - full featured, yet extensible and customizable
Home-page: https://github.com/pmxbot/pmxbot
Author: YouGov, Plc.
Author-email: dev@yougov.com
Maintainer: Jason R. Coombs
Maintainer-email: jaraco@jaraco.com
Classifier: Development Status :: 5 - Production/Stable
Classifier: Intended Audience :: Developers
Classifier: License :: OSI Approved :: MIT License
Classifier: Programming Language :: Python :: 3
Classifier: Programming Language :: Python :: 3 :: Only
Classifier: Topic :: Communications :: Chat :: Internet Relay Chat
Classifier: Topic :: Internet :: WWW/HTTP :: WSGI :: Application
Requires-Python: >=3.8
License-File: LICENSE
Requires-Dist: requests
Requires-Dist: pyyaml
Requires-Dist: feedparser
Requires-Dist: pytz
Requires-Dist: beautifulsoup4
Requires-Dist: wordnik-py3
Requires-Dist: more-itertools
Requires-Dist: tempora
Requires-Dist: jaraco.collections >=3.4
Requires-Dist: jaraco.itertools
Requires-Dist: jaraco.context
Requires-Dist: jaraco.classes
Requires-Dist: jaraco.functools
Requires-Dist: inflect
Requires-Dist: python-dateutil
Requires-Dist: jaraco.mongodb >=7.3.1
Requires-Dist: importlib-metadata >=3.6
Requires-Dist: importlib-resources >=1.3
Requires-Dist: dnspython
Provides-Extra: docs
Requires-Dist: sphinx >=3.5 ; extra == 'docs'
Requires-Dist: jaraco.packaging >=9.3 ; extra == 'docs'
Requires-Dist: rst.linker >=1.9 ; extra == 'docs'
Requires-Dist: furo ; extra == 'docs'
Requires-Dist: sphinx-lint ; extra == 'docs'
Requires-Dist: jaraco.tidelift >=1.4 ; extra == 'docs'
Provides-Extra: irc
Requires-Dist: irc >=15.0 ; extra == 'irc'
Provides-Extra: mongodb
Requires-Dist: pymongo >=3 ; extra == 'mongodb'
Provides-Extra: slack
Requires-Dist: slack-sdk ; extra == 'slack'
Provides-Extra: testing
Requires-Dist: pytest >=6 ; extra == 'testing'
Requires-Dist: pytest-checkdocs >=2.4 ; extra == 'testing'
Requires-Dist: pytest-cov ; extra == 'testing'
Requires-Dist: pytest-mypy ; extra == 'testing'
Requires-Dist: pytest-enabler >=2.2 ; extra == 'testing'
Requires-Dist: pytest-ruff >=0.2.1 ; extra == 'testing'
Requires-Dist: more-itertools ; extra == 'testing'
Requires-Dist: jaraco.mongodb ; extra == 'testing'
Requires-Dist: setuptools-scm ; extra == 'testing'
Requires-Dist: types-requests ; extra == 'testing'
Requires-Dist: types-python-dateutil ; extra == 'testing'
Requires-Dist: types-pytz ; extra == 'testing'
Requires-Dist: types-pyyaml ; extra == 'testing'
Requires-Dist: jaraco.test >=5.3 ; extra == 'testing'
Provides-Extra: viewer
Requires-Dist: cherrypy >=3.2.3 ; extra == 'viewer'
Requires-Dist: jinja2 >=2.11.2 ; extra == 'viewer'
